setup.cfg
setup.py
highfive/__init__.py
highfive/jobs.py
highfive/master.py
highfive/worker.py
highfive.egg-info/PKG-INFO
highfive.egg-info/SOURCES.txt
highfive.egg-info/dependency_links.txt
highfive.egg-info/top_level.txt