Metadata-Version: 1.1
Name: highfive
Version: 0.2
Summary: Framework for fault-tolerant cooperative distributed processing.
Home-page: https://github.com/abau171/highfive
Author: Andrew Bauer
Author-email: abau171@gmail.com
License: MIT
Download-URL: https://github.com/abau171/highfive/archive/v0.2.tar.gz
Keywords: distributed,queue,task queue,job queue,collaborative
Platform: UNKNOWN
Classifier: Development Status :: 3 - Alpha
Classifier: Intended Audience :: Developers
Classifier: License :: OSI Approved :: MIT License
Classifier: Programming Language :: Python :: 3 :: Only
Classifier: Topic :: Internet
Classifier: Topic :: Software Development
Classifier: Topic :: System :: Distributed Computing
